README.md
setup.py
systemusage/__init__.py
systemusage/cpu.py
systemusage/memory.py
systemusage.egg-info/PKG-INFO
systemusage.egg-info/SOURCES.txt
systemusage.egg-info/dependency_links.txt
systemusage.egg-info/requires.txt
systemusage.egg-info/top_level.txt