Metadata-Version: 2.1
Name: systemusage
Version: 0.1.0
Summary: A real-time system resource monitoring utility package
Home-page: https://github.com/PytechAcademy/PackagePublishing
Author: Pytech Academy
Author-email: pytechacademy@gmail.com
